evaltext/__init__.py
evaltext/base.py
evaltext/jsonl.py
evaltext/recorder.py
evaltext/runner.py
evaltext/scorer.py
evaltext/generator/__init__.py
evaltext/generator/cohere.py
evaltext/generator/generator.py
evaltext/generator/openai.py
evaltext/generator/openai_chat.py
evaltext-0.1.0.dist-info/METADATA
evaltext-0.1.0.dist-info/WHEEL
evaltext-0.1.0.dist-info/top_level.txt
evaltext-0.1.0.dist-info/RECORD
