Metadata-Version: 2.1
Name: evaltext
Version: 0.1.0
Summary: prompt evaluation tool.
Home-page: https://github.com/dotneet/evaltext
Author: Shinji Yamada
Author-email: dotneet@gmail.com
License: MIT
Platform: UNKNOWN
Classifier: Development Status :: 3 - Alpha
Classifier: Programming Language :: Python :: 3
Classifier: License :: OSI Approved :: MIT License
Classifier: Operating System :: OS Independent
Requires-Python: >=3.8
Requires-Dist: openai (==0.27.4)
Requires-Dist: cohere (==4.2.0)
Requires-Dist: python-dotenv (==1.0.0)
Requires-Dist: tiktoken (==0.3.3)
